[
  {
    "id": 1,
    "name": "Grand Palace Hotel",
    "location": "Chennai",
    "price": 8144,
    "image": "https://picsum.photos/800/500?random=4"
  },
  {
    "id": 2,
    "name": "Ocean View Resort",
    "location": "Chennai",
    "price": 4712,
    "image": "https://picsum.photos/800/500?random=4"
  },
  {
    "id": 3,
    "name": "City Comfort Inn",
    "location": "Pune",
    "price": 5760,
    "image": "https://picsum.photos/800/500?random=4"
  },
  {
    "id": 4,
    "name": "Royal Orchid Suites",
    "location": "Chennai",
    "price": 6574,
    "image": "https://picsum.photos/800/500?random=4"
  },
  {
    "id": 5,
    "name": "Mountain Peak Retreat",
    "location": "Pune",
    "price": 1842,
    "image": "https://picsum.photos/800/500?random=4"
  },
  {
    "id": 6,
    "name": "Sunshine Bay Hotel",
    "location": "Chennai",
    "price": 7236,
    "image": "https://picsum.photos/800/500?random=1"
  },
  {
    "id": 7,
    "name": "Palm Breeze Resort",
    "location": "Mumbai",
    "price": 4161,
    "image": "https://picsum.photos/800/500?random=1"
  },
  {
    "id": 8,
    "name": "Blue Lagoon Hotel",
    "location": "Hyderabad",
    "price": 3221,
    "image": "https://picsum.photos/800/500?random=4"
  },
  {
    "id": 9,
    "name": "Emerald Stay Suites",
    "location": "Delhi",
    "price": 6648,
    "image": "https://picsum.photos/800/500?random=2"
  },
  {
    "id": 10,
    "name": "Regal Crown Hotel",
    "location": "Delhi",
    "price": 7531,
    "image": "https://picsum.photos/800/500?random=2"
  },
  {
    "id": 11,
    "name": "Seaside Pearl Resort",
    "location": "Pune",
    "price": 5900,
    "image": "https://picsum.photos/800/500?random=2"
  },
  {
    "id": 12,
    "name": "Urban Nest Hotel",
    "location": "Bangalore",
    "price": 6471,
    "image": "https://picsum.photos/800/500?random=3"
  },
  {
    "id": 13,
    "name": "Green Leaf Residency",
    "location": "Bangalore",
    "price": 6498,
    "image": "https://picsum.photos/800/500?random=5"
  },
  {
    "id": 14,
    "name": "Silver Star Inn",
    "location": "Mumbai",
    "price": 2724,
    "image": "https://picsum.photos/800/500?random=4"
  },
  {
    "id": 15,
    "name": "Golden Horizon Resort",
    "location": "Hyderabad",
    "price": 6888,
    "image": "https://picsum.photos/800/500?random=5"
  },
  {
    "id": 16,
    "name": "Skyline Comfort Hotel",
    "location": "Mumbai",
    "price": 4821,
    "image": "https://picsum.photos/800/500?random=1"
  },
  {
    "id": 17,
    "name": "Lotus Bloom Suites",
    "location": "Kolkata",
    "price": 3254,
    "image": "https://picsum.photos/800/500?random=5"
  },
  {
    "id": 18,
    "name": "Tropical Paradise Resort",
    "location": "Goa",
    "price": 6775,
    "image": "https://picsum.photos/800/500?random=5"
  },
  {
    "id": 19,
    "name": "Moonlight Residency",
    "location": "Goa",
    "price": 8369,
    "image": "https://picsum.photos/800/500?random=4"
  },
  {
    "id": 20,
    "name": "Diamond City Inn",
    "location": "Hyderabad",
    "price": 5702,
    "image": "https://picsum.photos/800/500?random=2"
  }
]